<?xml version="1.0" encoding="UTF-8"?><ernm:NewReleaseMessage MessageSchemaVersionId="ern/341" LanguageAndScriptCode="en" xs:schemaLocation="http://ddex.net/xml/ern/341 http://ddex.net/xml/ern/341/release-notification.xsd" xmlns:ernm="http://ddex.net/xml/ern/341" xmlns:xs="http://www.w3.org/2001/XMLSchema-instance">	<MessageHeader>		<MessageThreadId>WMG000000000009</MessageThreadId>		<MessageId>BF97B06600A56841E04400144FEAB9A6</MessageId>		<MessageSender>			<PartyId>PADPIDA2007050901U</PartyId>			<PartyName>				<FullName>Warner Music Group</FullName>			</PartyName>		</MessageSender>		<MessageRecipient>			<PartyId>PADPIDA20100713035</PartyId>			<PartyName>				<FullName>1882-DPPS_Test - WMG</FullName>			</PartyName>		</MessageRecipient>		<MessageCreatedDateTime>2012-05-09T01:57:28Z</MessageCreatedDateTime>		<MessageControlType>LiveMessage</MessageControlType>	</MessageHeader>	<UpdateIndicator>OriginalMessage</UpdateIndicator>	<ResourceList>		<SoundRecording>			<SoundRecordingType>MusicalWorkSoundRecording</SoundRecordingType>			<SoundRecordingId>				<ISRC>USKEG0901377</ISRC>			</SoundRecordingId>			<ResourceReference>A1</ResourceReference>			<ReferenceTitle>				<TitleText>Krasnaya smorodina</TitleText>			</ReferenceTitle>			<Duration>PT3M16.005S</Duration>			<SoundRecordingDetailsByTerritory>				<TerritoryCode>Worldwide</TerritoryCode>				<Title TitleType="FormalTitle">					<TitleText>Krasnaya smorodina</TitleText>				</Title>				<Title TitleType="DisplayTitle">					<TitleText>Krasnaya smorodina</TitleText>				</Title>				<Title LanguageAndScriptCode="ru-cyrl" TitleType="DisplayTitle">					<TitleText LanguageAndScriptCode="ru-cyrl">Красная смородина</TitleText>				</Title>				<DisplayArtist>					<PartyName>						<FullName>Elena Kukarskaya</FullName>					</PartyName>					<PartyName>						<FullName LanguageAndScriptCode="ru-cyrl">Елена Кукарская</FullName>					</PartyName>					<PartyId Namespace="DPID:PADPIDA2007050901U">1276829</PartyId>					<ArtistRole>MainArtist</ArtistRole>				</DisplayArtist>				<LabelName>Monolit Records</LabelName>				<LabelName LabelNameType="MajorLabel">ADA US</LabelName>				<PLine>					<Year>2010</Year>					<PLineText>2010 Symbolic Music</PLineText>				</PLine>				<Genre>					<GenreText>Pop</GenreText>				</Genre>				<ParentalWarningType>NotExplicit</ParentalWarningType>				<TechnicalSoundRecordingDetails>					<TechnicalResourceDetailsReference>T1</TechnicalResourceDetailsReference>					<AudioCodecType Namespace="DPID:PADPIDA2007050901U" UserDefinedValue="FLAC">UserDefined</AudioCodecType>					<NumberOfChannels>2</NumberOfChannels>					<SamplingRate>44.1</SamplingRate>					<IsPreview>false</IsPreview>					<PreviewDetails>						<StartPoint>43</StartPoint>						<Duration>PT0H3M16.005S</Duration>						<ExpressionType>Informative</ExpressionType>					</PreviewDetails>					<File>						<FileName>814571011651_00001_LL.flac</FileName>						<HashSum>							<HashSum>737ac6db1bdef2b5d48ae6ba87d09a1b</HashSum>							<HashSumAlgorithmType>MD5</HashSumAlgorithmType>						</HashSum>					</File>				</TechnicalSoundRecordingDetails>			</SoundRecordingDetailsByTerritory>		</SoundRecording>		<SoundRecording>			<SoundRecordingType>MusicalWorkSoundRecording</SoundRecordingType>			<SoundRecordingId>				<ISRC>USKEG0901378</ISRC>			</SoundRecordingId>			<ResourceReference>A2</ResourceReference>			<ReferenceTitle>				<TitleText>Moy miliy drug</TitleText>			</ReferenceTitle>			<Duration>PT4M2.065S</Duration>			<SoundRecordingDetailsByTerritory>				<TerritoryCode>Worldwide</TerritoryCode>				<Title TitleType="FormalTitle">					<TitleText>Moy miliy drug</TitleText>				</Title>				<Title TitleType="DisplayTitle">					<TitleText>Moy miliy drug</TitleText>				</Title>				<Title LanguageAndScriptCode="ru-cyrl" TitleType="DisplayTitle">					<TitleText LanguageAndScriptCode="ru-cyrl">Мой милый друг</TitleText>				</Title>				<DisplayArtist>					<PartyName>						<FullName>Elena Kukarskaya</FullName>					</PartyName>					<PartyName>						<FullName LanguageAndScriptCode="ru-cyrl">Елена Кукарская</FullName>					</PartyName>					<PartyId Namespace="DPID:PADPIDA2007050901U">1276829</PartyId>					<ArtistRole>MainArtist</ArtistRole>				</DisplayArtist>				<LabelName>Monolit Records</LabelName>				<LabelName LabelNameType="MajorLabel">ADA US</LabelName>				<PLine>					<Year>2010</Year>					<PLineText>2010 Symbolic Music</PLineText>				</PLine>				<Genre>					<GenreText>Pop</GenreText>				</Genre>				<ParentalWarningType>NotExplicit</ParentalWarningType>				<TechnicalSoundRecordingDetails>					<TechnicalResourceDetailsReference>T2</TechnicalResourceDetailsReference>					<AudioCodecType Namespace="DPID:PADPIDA2007050901U" UserDefinedValue="FLAC">UserDefined</AudioCodecType>					<NumberOfChannels>2</NumberOfChannels>					<SamplingRate>44.1</SamplingRate>					<IsPreview>false</IsPreview>					<PreviewDetails>						<StartPoint>43</StartPoint>						<Duration>PT0H4M2.065S</Duration>						<ExpressionType>Informative</ExpressionType>					</PreviewDetails>					<File>						<FileName>814571011651_00002_LL.flac</FileName>						<HashSum>							<HashSum>ab7280d312f6bcf3074031234c92d527</HashSum>							<HashSumAlgorithmType>MD5</HashSumAlgorithmType>						</HashSum>					</File>				</TechnicalSoundRecordingDetails>			</SoundRecordingDetailsByTerritory>		</SoundRecording>		<SoundRecording>			<SoundRecordingType>MusicalWorkSoundRecording</SoundRecordingType>			<SoundRecordingId>				<ISRC>USKEG0901379</ISRC>			</SoundRecordingId>			<ResourceReference>A3</ResourceReference>			<ReferenceTitle>				<TitleText>Pianist</TitleText>			</ReferenceTitle>			<Duration>PT3M23.787S</Duration>			<SoundRecordingDetailsByTerritory>				<TerritoryCode>Worldwide</TerritoryCode>				<Title TitleType="FormalTitle">					<TitleText>Pianist</TitleText>				</Title>				<Title TitleType="DisplayTitle">					<TitleText>Pianist</TitleText>				</Title>				<Title LanguageAndScriptCode="ru-cyrl" TitleType="DisplayTitle">					<TitleText LanguageAndScriptCode="ru-cyrl">Пианист</TitleText>				</Title>				<DisplayArtist>					<PartyName>						<FullName>Elena Kukarskaya</FullName>					</PartyName>					<PartyName>						<FullName LanguageAndScriptCode="ru-cyrl">Елена Кукарская</FullName>					</PartyName>					<PartyId Namespace="DPID:PADPIDA2007050901U">1276829</PartyId>					<ArtistRole>MainArtist</ArtistRole>				</DisplayArtist>				<LabelName>Monolit Records</LabelName>				<LabelName LabelNameType="MajorLabel">ADA US</LabelName>				<PLine>					<Year>2010</Year>					<PLineText>2010 Symbolic Music</PLineText>				</PLine>				<Genre>					<GenreText>Pop</GenreText>				</Genre>				<ParentalWarningType>NotExplicit</ParentalWarningType>				<TechnicalSoundRecordingDetails>					<TechnicalResourceDetailsReference>T3</TechnicalResourceDetailsReference>					<AudioCodecType Namespace="DPID:PADPIDA2007050901U" UserDefinedValue="FLAC">UserDefined</AudioCodecType>					<NumberOfChannels>2</NumberOfChannels>					<SamplingRate>44.1</SamplingRate>					<IsPreview>false</IsPreview>					<PreviewDetails>						<StartPoint>43</StartPoint>						<Duration>PT0H3M23.787S</Duration>						<ExpressionType>Informative</ExpressionType>					</PreviewDetails>					<File>						<FileName>814571011651_00003_LL.flac</FileName>						<HashSum>							<HashSum>ca31173afedd76e8a997094400270a73</HashSum>							<HashSumAlgorithmType>MD5</HashSumAlgorithmType>						</HashSum>					</File>				</TechnicalSoundRecordingDetails>			</SoundRecordingDetailsByTerritory>		</SoundRecording>		<SoundRecording>			<SoundRecordingType>MusicalWorkSoundRecording</SoundRecordingType>			<SoundRecordingId>				<ISRC>USKEG0901380</ISRC>			</SoundRecordingId>			<ResourceReference>A4</ResourceReference>			<ReferenceTitle>				<TitleText>Po malen'koy</TitleText>			</ReferenceTitle>			<Duration>PT3M14.232S</Duration>			<SoundRecordingDetailsByTerritory>				<TerritoryCode>Worldwide</TerritoryCode>				<Title TitleType="FormalTitle">					<TitleText>Po malen'koy</TitleText>				</Title>				<Title TitleType="DisplayTitle">					<TitleText>Po malen'koy</TitleText>				</Title>				<Title LanguageAndScriptCode="ru-cyrl" TitleType="DisplayTitle">					<TitleText LanguageAndScriptCode="ru-cyrl">По маленькой</TitleText>				</Title>				<DisplayArtist>					<PartyName>						<FullName>Elena Kukarskaya</FullName>					</PartyName>					<PartyName>						<FullName LanguageAndScriptCode="ru-cyrl">Елена Кукарская</FullName>					</PartyName>					<PartyId Namespace="DPID:PADPIDA2007050901U">1276829</PartyId>					<ArtistRole>MainArtist</ArtistRole>				</DisplayArtist>				<LabelName>Monolit Records</LabelName>				<LabelName LabelNameType="MajorLabel">ADA US</LabelName>				<PLine>					<Year>2010</Year>					<PLineText>2010 Symbolic Music</PLineText>				</PLine>				<Genre>					<GenreText>Pop</GenreText>				</Genre>				<ParentalWarningType>NotExplicit</ParentalWarningType>				<TechnicalSoundRecordingDetails>					<TechnicalResourceDetailsReference>T4</TechnicalResourceDetailsReference>					<AudioCodecType Namespace="DPID:PADPIDA2007050901U" UserDefinedValue="FLAC">UserDefined</AudioCodecType>					<NumberOfChannels>2</NumberOfChannels>					<SamplingRate>44.1</SamplingRate>					<IsPreview>false</IsPreview>					<PreviewDetails>						<StartPoint>43</StartPoint>						<Duration>PT0H3M14.232S</Duration>						<ExpressionType>Informative</ExpressionType>					</PreviewDetails>					<File>						<FileName>814571011651_00004_LL.flac</FileName>						<HashSum>							<HashSum>69a43813d96fd2875385d6f22926b2ca</HashSum>							<HashSumAlgorithmType>MD5</HashSumAlgorithmType>						</HashSum>					</File>				</TechnicalSoundRecordingDetails>			</SoundRecordingDetailsByTerritory>		</SoundRecording>		<SoundRecording>			<SoundRecordingType>MusicalWorkSoundRecording</SoundRecordingType>			<SoundRecordingId>				<ISRC>USKEG0901381</ISRC>			</SoundRecordingId>			<ResourceReference>A5</ResourceReference>			<ReferenceTitle>				<TitleText>Raz, dva, tri</TitleText>			</ReferenceTitle>			<Duration>PT3M21.115S</Duration>			<SoundRecordingDetailsByTerritory>				<TerritoryCode>Worldwide</TerritoryCode>				<Title TitleType="FormalTitle">					<TitleText>Raz, dva, tri</TitleText>				</Title>				<Title TitleType="DisplayTitle">					<TitleText>Raz, dva, tri</TitleText>				</Title>				<Title LanguageAndScriptCode="ru-cyrl" TitleType="DisplayTitle">					<TitleText LanguageAndScriptCode="ru-cyrl">Раз, два, три</TitleText>				</Title>				<DisplayArtist>					<PartyName>						<FullName>Elena Kukarskaya</FullName>					</PartyName>					<PartyName>						<FullName LanguageAndScriptCode="ru-cyrl">Елена Кукарская</FullName>					</PartyName>					<PartyId Namespace="DPID:PADPIDA2007050901U">1276829</PartyId>					<ArtistRole>MainArtist</ArtistRole>				</DisplayArtist>				<LabelName>Monolit Records</LabelName>				<LabelName LabelNameType="MajorLabel">ADA US</LabelName>				<PLine>					<Year>2010</Year>					<PLineText>2010 Symbolic Music</PLineText>				</PLine>				<Genre>					<GenreText>Pop</GenreText>				</Genre>				<ParentalWarningType>NotExplicit</ParentalWarningType>				<TechnicalSoundRecordingDetails>					<TechnicalResourceDetailsReference>T5</TechnicalResourceDetailsReference>					<AudioCodecType Namespace="DPID:PADPIDA2007050901U" UserDefinedValue="FLAC">UserDefined</AudioCodecType>					<NumberOfChannels>2</NumberOfChannels>					<SamplingRate>44.1</SamplingRate>					<IsPreview>false</IsPreview>					<PreviewDetails>						<StartPoint>43</StartPoint>						<Duration>PT0H3M21.115S</Duration>						<ExpressionType>Informative</ExpressionType>					</PreviewDetails>					<File>						<FileName>814571011651_00005_LL.flac</FileName>						<HashSum>							<HashSum>5e0f82e533e8076fb0edb566b340518b</HashSum>							<HashSumAlgorithmType>MD5</HashSumAlgorithmType>						</HashSum>					</File>				</TechnicalSoundRecordingDetails>			</SoundRecordingDetailsByTerritory>		</SoundRecording>		<SoundRecording>			<SoundRecordingType>MusicalWorkSoundRecording</SoundRecordingType>			<SoundRecordingId>				<ISRC>USKEG0901382</ISRC>			</SoundRecordingId>			<ResourceReference>A6</ResourceReference>			<ReferenceTitle>				<TitleText>Ya ne ya</TitleText>			</ReferenceTitle>			<Duration>PT3M34.285S</Duration>			<SoundRecordingDetailsByTerritory>				<TerritoryCode>Worldwide</TerritoryCode>				<Title TitleType="FormalTitle">					<TitleText>Ya ne ya</TitleText>				</Title>				<Title TitleType="DisplayTitle">					<TitleText>Ya ne ya</TitleText>				</Title>				<Title LanguageAndScriptCode="ru-cyrl" TitleType="DisplayTitle">					<TitleText LanguageAndScriptCode="ru-cyrl">Я не я</TitleText>				</Title>				<DisplayArtist>					<PartyName>						<FullName>Elena Kukarskaya</FullName>					</PartyName>					<PartyName>						<FullName LanguageAndScriptCode="ru-cyrl">Елена Кукарская</FullName>					</PartyName>					<PartyId Namespace="DPID:PADPIDA2007050901U">1276829</PartyId>					<ArtistRole>MainArtist</ArtistRole>				</DisplayArtist>				<LabelName>Monolit Records</LabelName>				<LabelName LabelNameType="MajorLabel">ADA US</LabelName>				<PLine>					<Year>2010</Year>					<PLineText>2010 Symbolic Music</PLineText>				</PLine>				<Genre>					<GenreText>Pop</GenreText>				</Genre>				<ParentalWarningType>NotExplicit</ParentalWarningType>				<TechnicalSoundRecordingDetails>					<TechnicalResourceDetailsReference>T6</TechnicalResourceDetailsReference>					<AudioCodecType Namespace="DPID:PADPIDA2007050901U" UserDefinedValue="FLAC">UserDefined</AudioCodecType>					<NumberOfChannels>2</NumberOfChannels>					<SamplingRate>44.1</SamplingRate>					<IsPreview>false</IsPreview>					<PreviewDetails>						<StartPoint>43</StartPoint>						<Duration>PT0H3M34.285S</Duration>						<ExpressionType>Informative</ExpressionType>					</PreviewDetails>					<File>						<FileName>814571011651_00006_LL.flac</FileName>						<HashSum>							<HashSum>8ae88b5a2fbafa83d4e10b01df7feccd</HashSum>							<HashSumAlgorithmType>MD5</HashSumAlgorithmType>						</HashSum>					</File>				</TechnicalSoundRecordingDetails>			</SoundRecordingDetailsByTerritory>		</SoundRecording>		<SoundRecording>			<SoundRecordingType>MusicalWorkSoundRecording</SoundRecordingType>			<SoundRecordingId>				<ISRC>USKEG0901383</ISRC>			</SoundRecordingId>			<ResourceReference>A7</ResourceReference>			<ReferenceTitle>				<TitleText>Zhu-Zhu</TitleText>			</ReferenceTitle>			<Duration>PT3M24.426S</Duration>			<SoundRecordingDetailsByTerritory>				<TerritoryCode>Worldwide</TerritoryCode>				<Title TitleType="FormalTitle">					<TitleText>Zhu-Zhu</TitleText>				</Title>				<Title TitleType="DisplayTitle">					<TitleText>Zhu-Zhu</TitleText>				</Title>				<Title LanguageAndScriptCode="ru-cyrl" TitleType="DisplayTitle">					<TitleText LanguageAndScriptCode="ru-cyrl">ЖУ-ЖУ</TitleText>				</Title>				<DisplayArtist>					<PartyName>						<FullName>Elena Kukarskaya</FullName>					</PartyName>					<PartyName>						<FullName LanguageAndScriptCode="ru-cyrl">Елена Кукарская</FullName>					</PartyName>					<PartyId Namespace="DPID:PADPIDA2007050901U">1276829</PartyId>					<ArtistRole>MainArtist</ArtistRole>				</DisplayArtist>				<LabelName>Monolit Records</LabelName>				<LabelName LabelNameType="MajorLabel">ADA US</LabelName>				<PLine>					<Year>2010</Year>					<PLineText>2010 Symbolic Music</PLineText>				</PLine>				<Genre>					<GenreText>Pop</GenreText>				</Genre>				<ParentalWarningType>NotExplicit</ParentalWarningType>				<TechnicalSoundRecordingDetails>					<TechnicalResourceDetailsReference>T7</TechnicalResourceDetailsReference>					<AudioCodecType Namespace="DPID:PADPIDA2007050901U" UserDefinedValue="FLAC">UserDefined</AudioCodecType>					<NumberOfChannels>2</NumberOfChannels>					<SamplingRate>44.1</SamplingRate>					<IsPreview>false</IsPreview>					<PreviewDetails>						<StartPoint>43</StartPoint>						<Duration>PT0H3M24.426S</Duration>						<ExpressionType>Informative</ExpressionType>					</PreviewDetails>					<File>						<FileName>814571011651_00007_LL.flac</FileName>						<HashSum>							<HashSum>bb9a29ef254adadd5dbd9c19fba72b93</HashSum>							<HashSumAlgorithmType>MD5</HashSumAlgorithmType>						</HashSum>					</File>				</TechnicalSoundRecordingDetails>			</SoundRecordingDetailsByTerritory>		</SoundRecording>		<Image>			<ImageType>FrontCoverImage</ImageType>			<ImageId>				<ProprietaryId Namespace="DPID:PADPIDA2007050901U">814571011651.jpg</ProprietaryId>			</ImageId>			<ResourceReference>A8</ResourceReference>			<ImageDetailsByTerritory>				<TerritoryCode>Worldwide</TerritoryCode>				<TechnicalImageDetails>					<TechnicalResourceDetailsReference>T8</TechnicalResourceDetailsReference>					<ImageCodecType>JPEG</ImageCodecType>					<ImageHeight>1425</ImageHeight>					<ImageWidth>1425</ImageWidth>					<File>						<FileName>814571011651.jpg</FileName>						<HashSum>							<HashSum>45d9a9bf699a6ae10aa05ea7d7641539</HashSum>							<HashSumAlgorithmType>MD5</HashSumAlgorithmType>						</HashSum>					</File>				</TechnicalImageDetails>			</ImageDetailsByTerritory>		</Image>	</ResourceList>	<ReleaseList>		<Release>			<ReleaseId>				<GRid>A10302B0001066412J</GRid>				<ICPN IsEan="false">814571011651</ICPN>			</ReleaseId>			<ReleaseReference>R0</ReleaseReference>			<ReferenceTitle>				<TitleText>Izbrannoe</TitleText>			</ReferenceTitle>			<ReleaseResourceReferenceList>				<ReleaseResourceReference ReleaseResourceType="PrimaryResource">A1</ReleaseResourceReference>				<ReleaseResourceReference ReleaseResourceType="PrimaryResource">A2</ReleaseResourceReference>				<ReleaseResourceReference ReleaseResourceType="PrimaryResource">A3</ReleaseResourceReference>				<ReleaseResourceReference ReleaseResourceType="PrimaryResource">A4</ReleaseResourceReference>				<ReleaseResourceReference ReleaseResourceType="PrimaryResource">A5</ReleaseResourceReference>				<ReleaseResourceReference ReleaseResourceType="PrimaryResource">A6</ReleaseResourceReference>				<ReleaseResourceReference ReleaseResourceType="PrimaryResource">A7</ReleaseResourceReference>				<ReleaseResourceReference ReleaseResourceType="SecondaryResource">A8</ReleaseResourceReference>			</ReleaseResourceReferenceList>			<ReleaseType>Album</ReleaseType>			<ReleaseDetailsByTerritory>				<TerritoryCode>Worldwide</TerritoryCode>				<DisplayArtistName>Elena Kukarskaya</DisplayArtistName>				<LabelName>Monolit Records</LabelName>				<LabelName LabelNameType="MajorLabel">ADA US</LabelName>				<Title TitleType="FormalTitle">					<TitleText>Izbrannoe</TitleText>				</Title>				<Title TitleType="DisplayTitle">					<TitleText>Izbrannoe</TitleText>				</Title>				<Title LanguageAndScriptCode="ru-cyrl" TitleType="DisplayTitle">					<TitleText LanguageAndScriptCode="ru-cyrl">Избранное</TitleText>				</Title>				<Title TitleType="GroupingTitle">					<TitleText>Izbrannoe</TitleText>				</Title>				<DisplayArtist>					<PartyName>						<FullName>Elena Kukarskaya</FullName>					</PartyName>					<PartyName>						<FullName LanguageAndScriptCode="ru-cyrl">Елена Кукарская</FullName>					</PartyName>					<PartyId Namespace="DPID:PADPIDA2007050901U">1276829</PartyId>					<ArtistRole>MainArtist</ArtistRole>				</DisplayArtist>				<ParentalWarningType>NotExplicit</ParentalWarningType>				<ResourceGroup>					<ResourceGroup>						<SequenceNumber>1</SequenceNumber>						<ResourceGroupContentItem>							<SequenceNumber>1</SequenceNumber>							<ResourceType>SoundRecording</ResourceType>							<ReleaseResourceReference ReleaseResourceType="PrimaryResource">A1</ReleaseResourceReference>						</ResourceGroupContentItem>						<ResourceGroupContentItem>							<SequenceNumber>2</SequenceNumber>							<ResourceType>SoundRecording</ResourceType>							<ReleaseResourceReference ReleaseResourceType="PrimaryResource">A2</ReleaseResourceReference>						</ResourceGroupContentItem>						<ResourceGroupContentItem>							<SequenceNumber>3</SequenceNumber>							<ResourceType>SoundRecording</ResourceType>							<ReleaseResourceReference ReleaseResourceType="PrimaryResource">A3</ReleaseResourceReference>						</ResourceGroupContentItem>						<ResourceGroupContentItem>							<SequenceNumber>4</SequenceNumber>							<ResourceType>SoundRecording</ResourceType>							<ReleaseResourceReference ReleaseResourceType="PrimaryResource">A4</ReleaseResourceReference>						</ResourceGroupContentItem>						<ResourceGroupContentItem>							<SequenceNumber>5</SequenceNumber>							<ResourceType>SoundRecording</ResourceType>							<ReleaseResourceReference ReleaseResourceType="PrimaryResource">A5</ReleaseResourceReference>						</ResourceGroupContentItem>						<ResourceGroupContentItem>							<SequenceNumber>6</SequenceNumber>							<ResourceType>SoundRecording</ResourceType>							<ReleaseResourceReference ReleaseResourceType="PrimaryResource">A6</ReleaseResourceReference>						</ResourceGroupContentItem>						<ResourceGroupContentItem>							<SequenceNumber>7</SequenceNumber>							<ResourceType>SoundRecording</ResourceType>							<ReleaseResourceReference ReleaseResourceType="PrimaryResource">A7</ReleaseResourceReference>						</ResourceGroupContentItem>					</ResourceGroup>					<ResourceGroupContentItem>						<ResourceType>Image</ResourceType>						<ReleaseResourceReference ReleaseResourceType="SecondaryResource">A8</ReleaseResourceReference>					</ResourceGroupContentItem>				</ResourceGroup>				<Genre>					<GenreText>Pop</GenreText>				</Genre>				<OriginalReleaseDate>2010-02-23</OriginalReleaseDate>				<Keywords>Elena Kukarskaya Izbrannoe Pop </Keywords>			</ReleaseDetailsByTerritory>			<PLine>				<Year>2010</Year>				<PLineText>2010 Symbolic Music</PLineText>			</PLine>			<CLine>				<Year>2010</Year>				<CLineText>2010 Monolit</CLineText>			</CLine>		</Release>		<Release>			<ReleaseId>				<GRid>A10302B00010664195</GRid>				<ISRC>USKEG0901377</ISRC>			</ReleaseId>			<ReleaseReference>R1</ReleaseReference>			<ReferenceTitle>				<TitleText>Krasnaya smorodina</TitleText>			</ReferenceTitle>			<ReleaseResourceReferenceList>				<ReleaseResourceReference ReleaseResourceType="PrimaryResource">A1</ReleaseResourceReference>			</ReleaseResourceReferenceList>			<ReleaseType>TrackRelease</ReleaseType>			<ReleaseDetailsByTerritory>				<TerritoryCode>Worldwide</TerritoryCode>				<DisplayArtistName>Elena Kukarskaya</DisplayArtistName>				<LabelName>Monolit Records</LabelName>				<LabelName LabelNameType="MajorLabel">ADA US</LabelName>				<Title TitleType="FormalTitle">					<TitleText>Krasnaya smorodina</TitleText>				</Title>				<Title TitleType="DisplayTitle">					<TitleText>Krasnaya smorodina</TitleText>				</Title>				<Title LanguageAndScriptCode="ru-cyrl" TitleType="DisplayTitle">					<TitleText LanguageAndScriptCode="ru-cyrl">Красная смородина</TitleText>				</Title>				<DisplayArtist>					<PartyName>						<FullName>Elena Kukarskaya</FullName>					</PartyName>					<PartyName>						<FullName LanguageAndScriptCode="ru-cyrl">Елена Кукарская</FullName>					</PartyName>					<PartyId Namespace="DPID:PADPIDA2007050901U">1276829</PartyId>					<ArtistRole>MainArtist</ArtistRole>				</DisplayArtist>				<ResourceGroup>					<SequenceNumber>1</SequenceNumber>					<ResourceGroupContentItem>						<SequenceNumber>1</SequenceNumber>						<ResourceType>SoundRecording</ResourceType>						<ReleaseResourceReference ReleaseResourceType="PrimaryResource">A1</ReleaseResourceReference>					</ResourceGroupContentItem>				</ResourceGroup>				<Genre>					<GenreText>Pop</GenreText>				</Genre>				<Keywords>Elena Kukarskaya Krasnaya smorodina Pop </Keywords>			</ReleaseDetailsByTerritory>			<PLine>				<Year>2010</Year>				<PLineText>2010 Symbolic Music</PLineText>			</PLine>		</Release>		<Release>			<ReleaseId>				<GRid>A10302B0001066415D</GRid>				<ISRC>USKEG0901378</ISRC>			</ReleaseId>			<ReleaseReference>R2</ReleaseReference>			<ReferenceTitle>				<TitleText>Moy miliy drug</TitleText>			</ReferenceTitle>			<ReleaseResourceReferenceList>				<ReleaseResourceReference ReleaseResourceType="PrimaryResource">A2</ReleaseResourceReference>			</ReleaseResourceReferenceList>			<ReleaseType>TrackRelease</ReleaseType>			<ReleaseDetailsByTerritory>				<TerritoryCode>Worldwide</TerritoryCode>				<DisplayArtistName>Elena Kukarskaya</DisplayArtistName>				<LabelName>Monolit Records</LabelName>				<LabelName LabelNameType="MajorLabel">ADA US</LabelName>				<Title TitleType="FormalTitle">					<TitleText>Moy miliy drug</TitleText>				</Title>				<Title TitleType="DisplayTitle">					<TitleText>Moy miliy drug</TitleText>				</Title>				<Title LanguageAndScriptCode="ru-cyrl" TitleType="DisplayTitle">					<TitleText LanguageAndScriptCode="ru-cyrl">Мой милый друг</TitleText>				</Title>				<DisplayArtist>					<PartyName>						<FullName>Elena Kukarskaya</FullName>					</PartyName>					<PartyName>						<FullName LanguageAndScriptCode="ru-cyrl">Елена Кукарская</FullName>					</PartyName>					<PartyId Namespace="DPID:PADPIDA2007050901U">1276829</PartyId>					<ArtistRole>MainArtist</ArtistRole>				</DisplayArtist>				<ResourceGroup>					<SequenceNumber>1</SequenceNumber>					<ResourceGroupContentItem>						<SequenceNumber>1</SequenceNumber>						<ResourceType>SoundRecording</ResourceType>						<ReleaseResourceReference ReleaseResourceType="PrimaryResource">A2</ReleaseResourceReference>					</ResourceGroupContentItem>				</ResourceGroup>				<Genre>					<GenreText>Pop</GenreText>				</Genre>				<Keywords>Elena Kukarskaya Moy miliy drug Pop </Keywords>			</ReleaseDetailsByTerritory>			<PLine>				<Year>2010</Year>				<PLineText>2010 Symbolic Music</PLineText>			</PLine>		</Release>		<Release>			<ReleaseId>				<GRid>A10302B00010664179</GRid>				<ISRC>USKEG0901379</ISRC>			</ReleaseId>			<ReleaseReference>R3</ReleaseReference>			<ReferenceTitle>				<TitleText>Pianist</TitleText>			</ReferenceTitle>			<ReleaseResourceReferenceList>				<ReleaseResourceReference ReleaseResourceType="PrimaryResource">A3</ReleaseResourceReference>			</ReleaseResourceReferenceList>			<ReleaseType>TrackRelease</ReleaseType>			<ReleaseDetailsByTerritory>				<TerritoryCode>Worldwide</TerritoryCode>				<DisplayArtistName>Elena Kukarskaya</DisplayArtistName>				<LabelName>Monolit Records</LabelName>				<LabelName LabelNameType="MajorLabel">ADA US</LabelName>				<Title TitleType="FormalTitle">					<TitleText>Pianist</TitleText>				</Title>				<Title TitleType="DisplayTitle">					<TitleText>Pianist</TitleText>				</Title>				<Title LanguageAndScriptCode="ru-cyrl" TitleType="DisplayTitle">					<TitleText LanguageAndScriptCode="ru-cyrl">Пианист</TitleText>				</Title>				<DisplayArtist>					<PartyName>						<FullName>Elena Kukarskaya</FullName>					</PartyName>					<PartyName>						<FullName LanguageAndScriptCode="ru-cyrl">Елена Кукарская</FullName>					</PartyName>					<PartyId Namespace="DPID:PADPIDA2007050901U">1276829</PartyId>					<ArtistRole>MainArtist</ArtistRole>				</DisplayArtist>				<ResourceGroup>					<SequenceNumber>1</SequenceNumber>					<ResourceGroupContentItem>						<SequenceNumber>1</SequenceNumber>						<ResourceType>SoundRecording</ResourceType>						<ReleaseResourceReference ReleaseResourceType="PrimaryResource">A3</ReleaseResourceReference>					</ResourceGroupContentItem>				</ResourceGroup>				<Genre>					<GenreText>Pop</GenreText>				</Genre>				<Keywords>Elena Kukarskaya Pianist Pop </Keywords>			</ReleaseDetailsByTerritory>			<PLine>				<Year>2010</Year>				<PLineText>2010 Symbolic Music</PLineText>			</PLine>		</Release>		<Release>			<ReleaseId>				<GRid>A10302B00010664187</GRid>				<ISRC>USKEG0901380</ISRC>			</ReleaseId>			<ReleaseReference>R4</ReleaseReference>			<ReferenceTitle>				<TitleText>Po malen'koy</TitleText>			</ReferenceTitle>			<ReleaseResourceReferenceList>				<ReleaseResourceReference ReleaseResourceType="PrimaryResource">A4</ReleaseResourceReference>			</ReleaseResourceReferenceList>			<ReleaseType>TrackRelease</ReleaseType>			<ReleaseDetailsByTerritory>				<TerritoryCode>Worldwide</TerritoryCode>				<DisplayArtistName>Elena Kukarskaya</DisplayArtistName>				<LabelName>Monolit Records</LabelName>				<LabelName LabelNameType="MajorLabel">ADA US</LabelName>				<Title TitleType="FormalTitle">					<TitleText>Po malen'koy</TitleText>				</Title>				<Title TitleType="DisplayTitle">					<TitleText>Po malen'koy</TitleText>				</Title>				<Title LanguageAndScriptCode="ru-cyrl" TitleType="DisplayTitle">					<TitleText LanguageAndScriptCode="ru-cyrl">По маленькой</TitleText>				</Title>				<DisplayArtist>					<PartyName>						<FullName>Elena Kukarskaya</FullName>					</PartyName>					<PartyName>						<FullName LanguageAndScriptCode="ru-cyrl">Елена Кукарская</FullName>					</PartyName>					<PartyId Namespace="DPID:PADPIDA2007050901U">1276829</PartyId>					<ArtistRole>MainArtist</ArtistRole>				</DisplayArtist>				<ResourceGroup>					<SequenceNumber>1</SequenceNumber>					<ResourceGroupContentItem>						<SequenceNumber>1</SequenceNumber>						<ResourceType>SoundRecording</ResourceType>						<ReleaseResourceReference ReleaseResourceType="PrimaryResource">A4</ReleaseResourceReference>					</ResourceGroupContentItem>				</ResourceGroup>				<Genre>					<GenreText>Pop</GenreText>				</Genre>				<Keywords>Elena Kukarskaya Po malen'koy Pop </Keywords>			</ReleaseDetailsByTerritory>			<PLine>				<Year>2010</Year>				<PLineText>2010 Symbolic Music</PLineText>			</PLine>		</Release>		<Release>			<ReleaseId>				<GRid>A10302B0001066414F</GRid>				<ISRC>USKEG0901381</ISRC>			</ReleaseId>			<ReleaseReference>R5</ReleaseReference>			<ReferenceTitle>				<TitleText>Raz, dva, tri</TitleText>			</ReferenceTitle>			<ReleaseResourceReferenceList>				<ReleaseResourceReference ReleaseResourceType="PrimaryResource">A5</ReleaseResourceReference>			</ReleaseResourceReferenceList>			<ReleaseType>TrackRelease</ReleaseType>			<ReleaseDetailsByTerritory>				<TerritoryCode>Worldwide</TerritoryCode>				<DisplayArtistName>Elena Kukarskaya</DisplayArtistName>				<LabelName>Monolit Records</LabelName>				<LabelName LabelNameType="MajorLabel">ADA US</LabelName>				<Title TitleType="FormalTitle">					<TitleText>Raz, dva, tri</TitleText>				</Title>				<Title TitleType="DisplayTitle">					<TitleText>Raz, dva, tri</TitleText>				</Title>				<Title LanguageAndScriptCode="ru-cyrl" TitleType="DisplayTitle">					<TitleText LanguageAndScriptCode="ru-cyrl">Раз, два, три</TitleText>				</Title>				<DisplayArtist>					<PartyName>						<FullName>Elena Kukarskaya</FullName>					</PartyName>					<PartyName>						<FullName LanguageAndScriptCode="ru-cyrl">Елена Кукарская</FullName>					</PartyName>					<PartyId Namespace="DPID:PADPIDA2007050901U">1276829</PartyId>					<ArtistRole>MainArtist</ArtistRole>				</DisplayArtist>				<ResourceGroup>					<SequenceNumber>1</SequenceNumber>					<ResourceGroupContentItem>						<SequenceNumber>1</SequenceNumber>						<ResourceType>SoundRecording</ResourceType>						<ReleaseResourceReference ReleaseResourceType="PrimaryResource">A5</ReleaseResourceReference>					</ResourceGroupContentItem>				</ResourceGroup>				<Genre>					<GenreText>Pop</GenreText>				</Genre>				<Keywords>Elena Kukarskaya Raz, dva, tri Pop </Keywords>			</ReleaseDetailsByTerritory>			<PLine>				<Year>2010</Year>				<PLineText>2010 Symbolic Music</PLineText>			</PLine>		</Release>		<Release>			<ReleaseId>				<GRid>A10302B0001066413H</GRid>				<ISRC>USKEG0901382</ISRC>			</ReleaseId>			<ReleaseReference>R6</ReleaseReference>			<ReferenceTitle>				<TitleText>Ya ne ya</TitleText>			</ReferenceTitle>			<ReleaseResourceReferenceList>				<ReleaseResourceReference ReleaseResourceType="PrimaryResource">A6</ReleaseResourceReference>			</ReleaseResourceReferenceList>			<ReleaseType>TrackRelease</ReleaseType>			<ReleaseDetailsByTerritory>				<TerritoryCode>Worldwide</TerritoryCode>				<DisplayArtistName>Elena Kukarskaya</DisplayArtistName>				<LabelName>Monolit Records</LabelName>				<LabelName LabelNameType="MajorLabel">ADA US</LabelName>				<Title TitleType="FormalTitle">					<TitleText>Ya ne ya</TitleText>				</Title>				<Title TitleType="DisplayTitle">					<TitleText>Ya ne ya</TitleText>				</Title>				<Title LanguageAndScriptCode="ru-cyrl" TitleType="DisplayTitle">					<TitleText LanguageAndScriptCode="ru-cyrl">Я не я</TitleText>				</Title>				<DisplayArtist>					<PartyName>						<FullName>Elena Kukarskaya</FullName>					</PartyName>					<PartyName>						<FullName LanguageAndScriptCode="ru-cyrl">Елена Кукарская</FullName>					</PartyName>					<PartyId Namespace="DPID:PADPIDA2007050901U">1276829</PartyId>					<ArtistRole>MainArtist</ArtistRole>				</DisplayArtist>				<ResourceGroup>					<SequenceNumber>1</SequenceNumber>					<ResourceGroupContentItem>						<SequenceNumber>1</SequenceNumber>						<ResourceType>SoundRecording</ResourceType>						<ReleaseResourceReference ReleaseResourceType="PrimaryResource">A6</ReleaseResourceReference>					</ResourceGroupContentItem>				</ResourceGroup>				<Genre>					<GenreText>Pop</GenreText>				</Genre>				<Keywords>Elena Kukarskaya Ya ne ya Pop </Keywords>			</ReleaseDetailsByTerritory>			<PLine>				<Year>2010</Year>				<PLineText>2010 Symbolic Music</PLineText>			</PLine>		</Release>		<Release>			<ReleaseId>				<GRid>A10302B0001066416B</GRid>				<ISRC>USKEG0901383</ISRC>			</ReleaseId>			<ReleaseReference>R7</ReleaseReference>			<ReferenceTitle>				<TitleText>Zhu-Zhu</TitleText>			</ReferenceTitle>			<ReleaseResourceReferenceList>				<ReleaseResourceReference ReleaseResourceType="PrimaryResource">A7</ReleaseResourceReference>			</ReleaseResourceReferenceList>			<ReleaseType>TrackRelease</ReleaseType>			<ReleaseDetailsByTerritory>				<TerritoryCode>Worldwide</TerritoryCode>				<DisplayArtistName>Elena Kukarskaya</DisplayArtistName>				<LabelName>Monolit Records</LabelName>				<LabelName LabelNameType="MajorLabel">ADA US</LabelName>				<Title TitleType="FormalTitle">					<TitleText>Zhu-Zhu</TitleText>				</Title>				<Title TitleType="DisplayTitle">					<TitleText>Zhu-Zhu</TitleText>				</Title>				<Title LanguageAndScriptCode="ru-cyrl" TitleType="DisplayTitle">					<TitleText LanguageAndScriptCode="ru-cyrl">ЖУ-ЖУ</TitleText>				</Title>				<DisplayArtist>					<PartyName>						<FullName>Elena Kukarskaya</FullName>					</PartyName>					<PartyName>						<FullName LanguageAndScriptCode="ru-cyrl">Елена Кукарская</FullName>					</PartyName>					<PartyId Namespace="DPID:PADPIDA2007050901U">1276829</PartyId>					<ArtistRole>MainArtist</ArtistRole>				</DisplayArtist>				<ResourceGroup>					<SequenceNumber>1</SequenceNumber>					<ResourceGroupContentItem>						<SequenceNumber>1</SequenceNumber>						<ResourceType>SoundRecording</ResourceType>						<ReleaseResourceReference ReleaseResourceType="PrimaryResource">A7</ReleaseResourceReference>					</ResourceGroupContentItem>				</ResourceGroup>				<Genre>					<GenreText>Pop</GenreText>				</Genre>				<Keywords>Elena Kukarskaya Zhu-Zhu Pop </Keywords>			</ReleaseDetailsByTerritory>			<PLine>				<Year>2010</Year>				<PLineText>2010 Symbolic Music</PLineText>			</PLine>		</Release>	</ReleaseList>	<DealList>		<ReleaseDeal>			<DealReleaseReference>R0</DealReleaseReference>			<Deal>				<DealTerms>					<CommercialModelType>AdvertisementSupportedModel</CommercialModelType>					<Usage>						<UseType>NonInteractiveStream</UseType>						<UseType>OnDemandStream</UseType>					</Usage>					<TerritoryCode>CA</TerritoryCode>					<ValidityPeriod>						<StartDate>2010-02-23</StartDate>					</ValidityPeriod>					<PreOrderPreviewDate>2010-02-23</PreOrderPreviewDate>				</DealTerms>			</Deal>			<Deal>				<DealTerms>					<CommercialModelType>SubscriptionModel</CommercialModelType>					<Usage>						<UseType>NonInteractiveStream</UseType>						<UseType>OnDemandStream</UseType>						<UseType>ConditionalDownload</UseType>					</Usage>					<TerritoryCode>CA</TerritoryCode>					<ValidityPeriod>						<StartDate>2010-02-23</StartDate>					</ValidityPeriod>					<PreOrderPreviewDate>2010-02-23</PreOrderPreviewDate>				</DealTerms>			</Deal>			<Deal>				<DealTerms>					<CommercialModelType>PayAsYouGoModel</CommercialModelType>					<Usage>						<UseType>PermanentDownload</UseType>					</Usage>					<TerritoryCode>CA</TerritoryCode>					<PriceInformation>						<PriceType Namespace="DPID:PADPIDA2007050901U">A05</PriceType>					</PriceInformation>					<ValidityPeriod>						<StartDate>2010-02-23</StartDate>					</ValidityPeriod>					<PreOrderPreviewDate>2010-02-23</PreOrderPreviewDate>				</DealTerms>			</Deal>			<Deal>				<DealTerms>					<CommercialModelType>AdvertisementSupportedModel</CommercialModelType>					<Usage>						<UseType>NonInteractiveStream</UseType>						<UseType>OnDemandStream</UseType>					</Usage>					<TerritoryCode>DE</TerritoryCode>					<ValidityPeriod>						<StartDate>2010-02-23</StartDate>					</ValidityPeriod>					<PreOrderPreviewDate>2010-02-23</PreOrderPreviewDate>				</DealTerms>			</Deal>			<Deal>				<DealTerms>					<CommercialModelType>SubscriptionModel</CommercialModelType>					<Usage>						<UseType>NonInteractiveStream</UseType>						<UseType>OnDemandStream</UseType>						<UseType>ConditionalDownload</UseType>					</Usage>					<TerritoryCode>DE</TerritoryCode>					<ValidityPeriod>						<StartDate>2010-02-23</StartDate>					</ValidityPeriod>					<PreOrderPreviewDate>2010-02-23</PreOrderPreviewDate>				</DealTerms>			</Deal>			<Deal>				<DealTerms>					<CommercialModelType>PayAsYouGoModel</CommercialModelType>					<Usage>						<UseType>PermanentDownload</UseType>					</Usage>					<TerritoryCode>DE</TerritoryCode>					<PriceInformation>						<PriceType Namespace="DPID:PADPIDA2007050901U">A05</PriceType>					</PriceInformation>					<ValidityPeriod>						<StartDate>2010-02-23</StartDate>					</ValidityPeriod>					<PreOrderPreviewDate>2010-02-23</PreOrderPreviewDate>				</DealTerms>			</Deal>			<Deal>				<DealTerms>					<CommercialModelType>AdvertisementSupportedModel</CommercialModelType>					<Usage>						<UseType>NonInteractiveStream</UseType>						<UseType>OnDemandStream</UseType>					</Usage>					<TerritoryCode>FR</TerritoryCode>					<ValidityPeriod>						<StartDate>2010-02-23</StartDate>					</ValidityPeriod>					<PreOrderPreviewDate>2010-02-23</PreOrderPreviewDate>				</DealTerms>			</Deal>			<Deal>				<DealTerms>					<CommercialModelType>SubscriptionModel</CommercialModelType>					<Usage>						<UseType>NonInteractiveStream</UseType>						<UseType>OnDemandStream</UseType>						<UseType>ConditionalDownload</UseType>					</Usage>					<TerritoryCode>FR</TerritoryCode>					<ValidityPeriod>						<StartDate>2010-02-23</StartDate>					</ValidityPeriod>					<PreOrderPreviewDate>2010-02-23</PreOrderPreviewDate>				</DealTerms>			</Deal>			<Deal>				<DealTerms>					<CommercialModelType>PayAsYouGoModel</CommercialModelType>					<Usage>						<UseType>PermanentDownload</UseType>					</Usage>					<TerritoryCode>FR</TerritoryCode>					<PriceInformation>						<PriceType Namespace="DPID:PADPIDA2007050901U">A05</PriceType>					</PriceInformation>					<ValidityPeriod>						<StartDate>2010-02-23</StartDate>					</ValidityPeriod>					<PreOrderPreviewDate>2010-02-23</PreOrderPreviewDate>				</DealTerms>			</Deal>			<Deal>				<DealTerms>					<CommercialModelType>AdvertisementSupportedModel</CommercialModelType>					<Usage>						<UseType>NonInteractiveStream</UseType>						<UseType>OnDemandStream</UseType>					</Usage>					<TerritoryCode>GB</TerritoryCode>					<ValidityPeriod>						<StartDate>2010-02-23</StartDate>					</ValidityPeriod>					<PreOrderPreviewDate>2010-02-23</PreOrderPreviewDate>				</DealTerms>			</Deal>			<Deal>				<DealTerms>					<CommercialModelType>SubscriptionModel</CommercialModelType>					<Usage>						<UseType>NonInteractiveStream</UseType>						<UseType>OnDemandStream</UseType>						<UseType>ConditionalDownload</UseType>					</Usage>					<TerritoryCode>GB</TerritoryCode>					<ValidityPeriod>						<StartDate>2010-02-23</StartDate>					</ValidityPeriod>					<PreOrderPreviewDate>2010-02-23</PreOrderPreviewDate>				</DealTerms>			</Deal>			<Deal>				<DealTerms>					<CommercialModelType>PayAsYouGoModel</CommercialModelType>					<Usage>						<UseType>PermanentDownload</UseType>					</Usage>					<TerritoryCode>GB</TerritoryCode>					<PriceInformation>						<PriceType Namespace="DPID:PADPIDA2007050901U">A05</PriceType>					</PriceInformation>					<ValidityPeriod>						<StartDate>2010-02-23</StartDate>					</ValidityPeriod>					<PreOrderPreviewDate>2010-02-23</PreOrderPreviewDate>				</DealTerms>			</Deal>			<Deal>				<DealTerms>					<CommercialModelType>AdvertisementSupportedModel</CommercialModelType>					<Usage>						<UseType>NonInteractiveStream</UseType>						<UseType>OnDemandStream</UseType>					</Usage>					<TerritoryCode>US</TerritoryCode>					<ValidityPeriod>						<StartDate>2010-02-23</StartDate>					</ValidityPeriod>					<PreOrderPreviewDate>2010-02-23</PreOrderPreviewDate>				</DealTerms>			</Deal>			<Deal>				<DealTerms>					<CommercialModelType>SubscriptionModel</CommercialModelType>					<Usage>						<UseType>NonInteractiveStream</UseType>						<UseType>OnDemandStream</UseType>						<UseType>ConditionalDownload</UseType>					</Usage>					<TerritoryCode>US</TerritoryCode>					<ValidityPeriod>						<StartDate>2010-02-23</StartDate>					</ValidityPeriod>					<PreOrderPreviewDate>2010-02-23</PreOrderPreviewDate>				</DealTerms>			</Deal>			<Deal>				<DealTerms>					<CommercialModelType>PayAsYouGoModel</CommercialModelType>					<Usage>						<UseType>PermanentDownload</UseType>					</Usage>					<TerritoryCode>US</TerritoryCode>					<PriceInformation>						<PriceType Namespace="DPID:PADPIDA2007050901U">B7</PriceType>					</PriceInformation>					<ValidityPeriod>						<StartDate>2010-02-23</StartDate>					</ValidityPeriod>					<PreOrderPreviewDate>2010-02-23</PreOrderPreviewDate>				</DealTerms>			</Deal>			<EffectiveDate>2012-05-09</EffectiveDate>		</ReleaseDeal>		<ReleaseDeal>			<DealReleaseReference>R1</DealReleaseReference>			<Deal>				<DealTerms>					<CommercialModelType>AdvertisementSupportedModel</CommercialModelType>					<Usage>						<UseType>NonInteractiveStream</UseType>						<UseType>OnDemandStream</UseType>					</Usage>					<TerritoryCode>CA</TerritoryCode>					<ValidityPeriod>						<StartDate>2010-02-23</StartDate>					</ValidityPeriod>				</DealTerms>			</Deal>			<Deal>				<DealTerms>					<CommercialModelType>SubscriptionModel</CommercialModelType>					<Usage>						<UseType>NonInteractiveStream</UseType>						<UseType>OnDemandStream</UseType>						<UseType>ConditionalDownload</UseType>					</Usage>					<TerritoryCode>CA</TerritoryCode>					<ValidityPeriod>						<StartDate>2010-02-23</StartDate>					</ValidityPeriod>				</DealTerms>			</Deal>			<Deal>				<DealTerms>					<CommercialModelType>PayAsYouGoModel</CommercialModelType>					<Usage>						<UseType>PermanentDownload</UseType>					</Usage>					<TerritoryCode>CA</TerritoryCode>					<PriceInformation>						<PriceType Namespace="DPID:PADPIDA2007050901U">S01</PriceType>					</PriceInformation>					<ValidityPeriod>						<StartDate>2010-02-23</StartDate>					</ValidityPeriod>				</DealTerms>			</Deal>			<Deal>				<DealTerms>					<CommercialModelType>AdvertisementSupportedModel</CommercialModelType>					<Usage>						<UseType>NonInteractiveStream</UseType>						<UseType>OnDemandStream</UseType>					</Usage>					<TerritoryCode>DE</TerritoryCode>					<ValidityPeriod>						<StartDate>2010-02-23</StartDate>					</ValidityPeriod>				</DealTerms>			</Deal>			<Deal>				<DealTerms>					<CommercialModelType>SubscriptionModel</CommercialModelType>					<Usage>						<UseType>NonInteractiveStream</UseType>						<UseType>OnDemandStream</UseType>						<UseType>ConditionalDownload</UseType>					</Usage>					<TerritoryCode>DE</TerritoryCode>					<ValidityPeriod>						<StartDate>2010-02-23</StartDate>					</ValidityPeriod>				</DealTerms>			</Deal>			<Deal>				<DealTerms>					<CommercialModelType>PayAsYouGoModel</CommercialModelType>					<Usage>						<UseType>PermanentDownload</UseType>					</Usage>					<TerritoryCode>DE</TerritoryCode>					<PriceInformation>						<PriceType Namespace="DPID:PADPIDA2007050901U">S01</PriceType>					</PriceInformation>					<ValidityPeriod>						<StartDate>2010-02-23</StartDate>					</ValidityPeriod>				</DealTerms>			</Deal>			<Deal>				<DealTerms>					<CommercialModelType>AdvertisementSupportedModel</CommercialModelType>					<Usage>						<UseType>NonInteractiveStream</UseType>						<UseType>OnDemandStream</UseType>					</Usage>					<TerritoryCode>FR</TerritoryCode>					<ValidityPeriod>						<StartDate>2010-02-23</StartDate>					</ValidityPeriod>				</DealTerms>			</Deal>			<Deal>				<DealTerms>					<CommercialModelType>SubscriptionModel</CommercialModelType>					<Usage>						<UseType>NonInteractiveStream</UseType>						<UseType>OnDemandStream</UseType>						<UseType>ConditionalDownload</UseType>					</Usage>					<TerritoryCode>FR</TerritoryCode>					<ValidityPeriod>						<StartDate>2010-02-23</StartDate>					</ValidityPeriod>				</DealTerms>			</Deal>			<Deal>				<DealTerms>					<CommercialModelType>PayAsYouGoModel</CommercialModelType>					<Usage>						<UseType>PermanentDownload</UseType>					</Usage>					<TerritoryCode>FR</TerritoryCode>					<PriceInformation>						<PriceType Namespace="DPID:PADPIDA2007050901U">S01</PriceType>					</PriceInformation>					<ValidityPeriod>						<StartDate>2010-02-23</StartDate>					</ValidityPeriod>				</DealTerms>			</Deal>			<Deal>				<DealTerms>					<CommercialModelType>AdvertisementSupportedModel</CommercialModelType>					<Usage>						<UseType>NonInteractiveStream</UseType>						<UseType>OnDemandStream</UseType>					</Usage>					<TerritoryCode>GB</TerritoryCode>					<ValidityPeriod>						<StartDate>2010-02-23</StartDate>					</ValidityPeriod>				</DealTerms>			</Deal>			<Deal>				<DealTerms>					<CommercialModelType>SubscriptionModel</CommercialModelType>					<Usage>						<UseType>NonInteractiveStream</UseType>						<UseType>OnDemandStream</UseType>						<UseType>ConditionalDownload</UseType>					</Usage>					<TerritoryCode>GB</TerritoryCode>					<ValidityPeriod>						<StartDate>2010-02-23</StartDate>					</ValidityPeriod>				</DealTerms>			</Deal>			<Deal>				<DealTerms>					<CommercialModelType>PayAsYouGoModel</CommercialModelType>					<Usage>						<UseType>PermanentDownload</UseType>					</Usage>					<TerritoryCode>GB</TerritoryCode>					<PriceInformation>						<PriceType Namespace="DPID:PADPIDA2007050901U">S01</PriceType>					</PriceInformation>					<ValidityPeriod>						<StartDate>2010-02-23</StartDate>					</ValidityPeriod>				</DealTerms>			</Deal>			<Deal>				<DealTerms>					<CommercialModelType>AdvertisementSupportedModel</CommercialModelType>					<Usage>						<UseType>NonInteractiveStream</UseType>						<UseType>OnDemandStream</UseType>					</Usage>					<TerritoryCode>US</TerritoryCode>					<ValidityPeriod>						<StartDate>2010-02-23</StartDate>					</ValidityPeriod>				</DealTerms>			</Deal>			<Deal>				<DealTerms>					<CommercialModelType>SubscriptionModel</CommercialModelType>					<Usage>						<UseType>NonInteractiveStream</UseType>						<UseType>OnDemandStream</UseType>						<UseType>ConditionalDownload</UseType>					</Usage>					<TerritoryCode>US</TerritoryCode>					<ValidityPeriod>						<StartDate>2010-02-23</StartDate>					</ValidityPeriod>				</DealTerms>			</Deal>			<Deal>				<DealTerms>					<CommercialModelType>PayAsYouGoModel</CommercialModelType>					<Usage>						<UseType>PermanentDownload</UseType>					</Usage>					<TerritoryCode>US</TerritoryCode>					<PriceInformation>						<PriceType Namespace="DPID:PADPIDA2007050901U">S1</PriceType>					</PriceInformation>					<ValidityPeriod>						<StartDate>2010-02-23</StartDate>					</ValidityPeriod>				</DealTerms>			</Deal>			<EffectiveDate>2012-05-09</EffectiveDate>		</ReleaseDeal>		<ReleaseDeal>			<DealReleaseReference>R2</DealReleaseReference>			<Deal>				<DealTerms>					<CommercialModelType>AdvertisementSupportedModel</CommercialModelType>					<Usage>						<UseType>NonInteractiveStream</UseType>						<UseType>OnDemandStream</UseType>					</Usage>					<TerritoryCode>CA</TerritoryCode>					<ValidityPeriod>						<StartDate>2010-02-23</StartDate>					</ValidityPeriod>				</DealTerms>			</Deal>			<Deal>				<DealTerms>					<CommercialModelType>SubscriptionModel</CommercialModelType>					<Usage>						<UseType>NonInteractiveStream</UseType>						<UseType>OnDemandStream</UseType>						<UseType>ConditionalDownload</UseType>					</Usage>					<TerritoryCode>CA</TerritoryCode>					<ValidityPeriod>						<StartDate>2010-02-23</StartDate>					</ValidityPeriod>				</DealTerms>			</Deal>			<Deal>				<DealTerms>					<CommercialModelType>PayAsYouGoModel</CommercialModelType>					<Usage>						<UseType>PermanentDownload</UseType>					</Usage>					<TerritoryCode>CA</TerritoryCode>					<PriceInformation>						<PriceType Namespace="DPID:PADPIDA2007050901U">S01</PriceType>					</PriceInformation>					<ValidityPeriod>						<StartDate>2010-02-23</StartDate>					</ValidityPeriod>				</DealTerms>			</Deal>			<Deal>				<DealTerms>					<CommercialModelType>AdvertisementSupportedModel</CommercialModelType>					<Usage>						<UseType>NonInteractiveStream</UseType>						<UseType>OnDemandStream</UseType>					</Usage>					<TerritoryCode>DE</TerritoryCode>					<ValidityPeriod>						<StartDate>2010-02-23</StartDate>					</ValidityPeriod>				</DealTerms>			</Deal>			<Deal>				<DealTerms>					<CommercialModelType>SubscriptionModel</CommercialModelType>					<Usage>						<UseType>NonInteractiveStream</UseType>						<UseType>OnDemandStream</UseType>						<UseType>ConditionalDownload</UseType>					</Usage>					<TerritoryCode>DE</TerritoryCode>					<ValidityPeriod>						<StartDate>2010-02-23</StartDate>					</ValidityPeriod>				</DealTerms>			</Deal>			<Deal>				<DealTerms>					<CommercialModelType>PayAsYouGoModel</CommercialModelType>					<Usage>						<UseType>PermanentDownload</UseType>					</Usage>					<TerritoryCode>DE</TerritoryCode>					<PriceInformation>						<PriceType Namespace="DPID:PADPIDA2007050901U">S01</PriceType>					</PriceInformation>					<ValidityPeriod>						<StartDate>2010-02-23</StartDate>					</ValidityPeriod>				</DealTerms>			</Deal>			<Deal>				<DealTerms>					<CommercialModelType>AdvertisementSupportedModel</CommercialModelType>					<Usage>						<UseType>NonInteractiveStream</UseType>						<UseType>OnDemandStream</UseType>					</Usage>					<TerritoryCode>FR</TerritoryCode>					<ValidityPeriod>						<StartDate>2010-02-23</StartDate>					</ValidityPeriod>				</DealTerms>			</Deal>			<Deal>				<DealTerms>					<CommercialModelType>SubscriptionModel</CommercialModelType>					<Usage>						<UseType>NonInteractiveStream</UseType>						<UseType>OnDemandStream</UseType>						<UseType>ConditionalDownload</UseType>					</Usage>					<TerritoryCode>FR</TerritoryCode>					<ValidityPeriod>						<StartDate>2010-02-23</StartDate>					</ValidityPeriod>				</DealTerms>			</Deal>			<Deal>				<DealTerms>					<CommercialModelType>PayAsYouGoModel</CommercialModelType>					<Usage>						<UseType>PermanentDownload</UseType>					</Usage>					<TerritoryCode>FR</TerritoryCode>					<PriceInformation>						<PriceType Namespace="DPID:PADPIDA2007050901U">S01</PriceType>					</PriceInformation>					<ValidityPeriod>						<StartDate>2010-02-23</StartDate>					</ValidityPeriod>				</DealTerms>			</Deal>			<Deal>				<DealTerms>					<CommercialModelType>AdvertisementSupportedModel</CommercialModelType>					<Usage>						<UseType>NonInteractiveStream</UseType>						<UseType>OnDemandStream</UseType>					</Usage>					<TerritoryCode>GB</TerritoryCode>					<ValidityPeriod>						<StartDate>2010-02-23</StartDate>					</ValidityPeriod>				</DealTerms>			</Deal>			<Deal>				<DealTerms>					<CommercialModelType>SubscriptionModel</CommercialModelType>					<Usage>						<UseType>NonInteractiveStream</UseType>						<UseType>OnDemandStream</UseType>						<UseType>ConditionalDownload</UseType>					</Usage>					<TerritoryCode>GB</TerritoryCode>					<ValidityPeriod>						<StartDate>2010-02-23</StartDate>					</ValidityPeriod>				</DealTerms>			</Deal>			<Deal>				<DealTerms>					<CommercialModelType>PayAsYouGoModel</CommercialModelType>					<Usage>						<UseType>PermanentDownload</UseType>					</Usage>					<TerritoryCode>GB</TerritoryCode>					<PriceInformation>						<PriceType Namespace="DPID:PADPIDA2007050901U">S01</PriceType>					</PriceInformation>					<ValidityPeriod>						<StartDate>2010-02-23</StartDate>					</ValidityPeriod>				</DealTerms>			</Deal>			<Deal>				<DealTerms>					<CommercialModelType>AdvertisementSupportedModel</CommercialModelType>					<Usage>						<UseType>NonInteractiveStream</UseType>						<UseType>OnDemandStream</UseType>					</Usage>					<TerritoryCode>US</TerritoryCode>					<ValidityPeriod>						<StartDate>2010-02-23</StartDate>					</ValidityPeriod>				</DealTerms>			</Deal>			<Deal>				<DealTerms>					<CommercialModelType>SubscriptionModel</CommercialModelType>					<Usage>						<UseType>NonInteractiveStream</UseType>						<UseType>OnDemandStream</UseType>						<UseType>ConditionalDownload</UseType>					</Usage>					<TerritoryCode>US</TerritoryCode>					<ValidityPeriod>						<StartDate>2010-02-23</StartDate>					</ValidityPeriod>				</DealTerms>			</Deal>			<Deal>				<DealTerms>					<CommercialModelType>PayAsYouGoModel</CommercialModelType>					<Usage>						<UseType>PermanentDownload</UseType>					</Usage>					<TerritoryCode>US</TerritoryCode>					<PriceInformation>						<PriceType Namespace="DPID:PADPIDA2007050901U">S1</PriceType>					</PriceInformation>					<ValidityPeriod>						<StartDate>2010-02-23</StartDate>					</ValidityPeriod>				</DealTerms>			</Deal>			<EffectiveDate>2012-05-09</EffectiveDate>		</ReleaseDeal>		<ReleaseDeal>			<DealReleaseReference>R3</DealReleaseReference>			<Deal>				<DealTerms>					<CommercialModelType>AdvertisementSupportedModel</CommercialModelType>					<Usage>						<UseType>NonInteractiveStream</UseType>						<UseType>OnDemandStream</UseType>					</Usage>					<TerritoryCode>CA</TerritoryCode>					<ValidityPeriod>						<StartDate>2010-02-23</StartDate>					</ValidityPeriod>				</DealTerms>			</Deal>			<Deal>				<DealTerms>					<CommercialModelType>SubscriptionModel</CommercialModelType>					<Usage>						<UseType>NonInteractiveStream</UseType>						<UseType>OnDemandStream</UseType>						<UseType>ConditionalDownload</UseType>					</Usage>					<TerritoryCode>CA</TerritoryCode>					<ValidityPeriod>						<StartDate>2010-02-23</StartDate>					</ValidityPeriod>				</DealTerms>			</Deal>			<Deal>				<DealTerms>					<CommercialModelType>PayAsYouGoModel</CommercialModelType>					<Usage>						<UseType>PermanentDownload</UseType>					</Usage>					<TerritoryCode>CA</TerritoryCode>					<PriceInformation>						<PriceType Namespace="DPID:PADPIDA2007050901U">S01</PriceType>					</PriceInformation>					<ValidityPeriod>						<StartDate>2010-02-23</StartDate>					</ValidityPeriod>				</DealTerms>			</Deal>			<Deal>				<DealTerms>					<CommercialModelType>AdvertisementSupportedModel</CommercialModelType>					<Usage>						<UseType>NonInteractiveStream</UseType>						<UseType>OnDemandStream</UseType>					</Usage>					<TerritoryCode>DE</TerritoryCode>					<ValidityPeriod>						<StartDate>2010-02-23</StartDate>					</ValidityPeriod>				</DealTerms>			</Deal>			<Deal>				<DealTerms>					<CommercialModelType>SubscriptionModel</CommercialModelType>					<Usage>						<UseType>NonInteractiveStream</UseType>						<UseType>OnDemandStream</UseType>						<UseType>ConditionalDownload</UseType>					</Usage>					<TerritoryCode>DE</TerritoryCode>					<ValidityPeriod>						<StartDate>2010-02-23</StartDate>					</ValidityPeriod>				</DealTerms>			</Deal>			<Deal>				<DealTerms>					<CommercialModelType>PayAsYouGoModel</CommercialModelType>					<Usage>						<UseType>PermanentDownload</UseType>					</Usage>					<TerritoryCode>DE</TerritoryCode>					<PriceInformation>						<PriceType Namespace="DPID:PADPIDA2007050901U">S01</PriceType>					</PriceInformation>					<ValidityPeriod>						<StartDate>2010-02-23</StartDate>					</ValidityPeriod>				</DealTerms>			</Deal>			<Deal>				<DealTerms>					<CommercialModelType>AdvertisementSupportedModel</CommercialModelType>					<Usage>						<UseType>NonInteractiveStream</UseType>						<UseType>OnDemandStream</UseType>					</Usage>					<TerritoryCode>FR</TerritoryCode>					<ValidityPeriod>						<StartDate>2010-02-23</StartDate>					</ValidityPeriod>				</DealTerms>			</Deal>			<Deal>				<DealTerms>					<CommercialModelType>SubscriptionModel</CommercialModelType>					<Usage>						<UseType>NonInteractiveStream</UseType>						<UseType>OnDemandStream</UseType>						<UseType>ConditionalDownload</UseType>					</Usage>					<TerritoryCode>FR</TerritoryCode>					<ValidityPeriod>						<StartDate>2010-02-23</StartDate>					</ValidityPeriod>				</DealTerms>			</Deal>			<Deal>				<DealTerms>					<CommercialModelType>PayAsYouGoModel</CommercialModelType>					<Usage>						<UseType>PermanentDownload</UseType>					</Usage>					<TerritoryCode>FR</TerritoryCode>					<PriceInformation>						<PriceType Namespace="DPID:PADPIDA2007050901U">S01</PriceType>					</PriceInformation>					<ValidityPeriod>						<StartDate>2010-02-23</StartDate>					</ValidityPeriod>				</DealTerms>			</Deal>			<Deal>				<DealTerms>					<CommercialModelType>AdvertisementSupportedModel</CommercialModelType>					<Usage>						<UseType>NonInteractiveStream</UseType>						<UseType>OnDemandStream</UseType>					</Usage>					<TerritoryCode>GB</TerritoryCode>					<ValidityPeriod>						<StartDate>2010-02-23</StartDate>					</ValidityPeriod>				</DealTerms>			</Deal>			<Deal>				<DealTerms>					<CommercialModelType>SubscriptionModel</CommercialModelType>					<Usage>						<UseType>NonInteractiveStream</UseType>						<UseType>OnDemandStream</UseType>						<UseType>ConditionalDownload</UseType>					</Usage>					<TerritoryCode>GB</TerritoryCode>					<ValidityPeriod>						<StartDate>2010-02-23</StartDate>					</ValidityPeriod>				</DealTerms>			</Deal>			<Deal>				<DealTerms>					<CommercialModelType>PayAsYouGoModel</CommercialModelType>					<Usage>						<UseType>PermanentDownload</UseType>					</Usage>					<TerritoryCode>GB</TerritoryCode>					<PriceInformation>						<PriceType Namespace="DPID:PADPIDA2007050901U">S01</PriceType>					</PriceInformation>					<ValidityPeriod>						<StartDate>2010-02-23</StartDate>					</ValidityPeriod>				</DealTerms>			</Deal>			<Deal>				<DealTerms>					<CommercialModelType>AdvertisementSupportedModel</CommercialModelType>					<Usage>						<UseType>NonInteractiveStream</UseType>						<UseType>OnDemandStream</UseType>					</Usage>					<TerritoryCode>US</TerritoryCode>					<ValidityPeriod>						<StartDate>2010-02-23</StartDate>					</ValidityPeriod>				</DealTerms>			</Deal>			<Deal>				<DealTerms>					<CommercialModelType>SubscriptionModel</CommercialModelType>					<Usage>						<UseType>NonInteractiveStream</UseType>						<UseType>OnDemandStream</UseType>						<UseType>ConditionalDownload</UseType>					</Usage>					<TerritoryCode>US</TerritoryCode>					<ValidityPeriod>						<StartDate>2010-02-23</StartDate>					</ValidityPeriod>				</DealTerms>			</Deal>			<Deal>				<DealTerms>					<CommercialModelType>PayAsYouGoModel</CommercialModelType>					<Usage>						<UseType>PermanentDownload</UseType>					</Usage>					<TerritoryCode>US</TerritoryCode>					<PriceInformation>						<PriceType Namespace="DPID:PADPIDA2007050901U">S1</PriceType>					</PriceInformation>					<ValidityPeriod>						<StartDate>2010-02-23</StartDate>					</ValidityPeriod>				</DealTerms>			</Deal>			<EffectiveDate>2012-05-09</EffectiveDate>		</ReleaseDeal>		<ReleaseDeal>			<DealReleaseReference>R4</DealReleaseReference>			<Deal>				<DealTerms>					<CommercialModelType>AdvertisementSupportedModel</CommercialModelType>					<Usage>						<UseType>NonInteractiveStream</UseType>						<UseType>OnDemandStream</UseType>					</Usage>					<TerritoryCode>CA</TerritoryCode>					<ValidityPeriod>						<StartDate>2010-02-23</StartDate>					</ValidityPeriod>				</DealTerms>			</Deal>			<Deal>				<DealTerms>					<CommercialModelType>SubscriptionModel</CommercialModelType>					<Usage>						<UseType>NonInteractiveStream</UseType>						<UseType>OnDemandStream</UseType>						<UseType>ConditionalDownload</UseType>					</Usage>					<TerritoryCode>CA</TerritoryCode>					<ValidityPeriod>						<StartDate>2010-02-23</StartDate>					</ValidityPeriod>				</DealTerms>			</Deal>			<Deal>				<DealTerms>					<CommercialModelType>PayAsYouGoModel</CommercialModelType>					<Usage>						<UseType>PermanentDownload</UseType>					</Usage>					<TerritoryCode>CA</TerritoryCode>					<PriceInformation>						<PriceType Namespace="DPID:PADPIDA2007050901U">S01</PriceType>					</PriceInformation>					<ValidityPeriod>						<StartDate>2010-02-23</StartDate>					</ValidityPeriod>				</DealTerms>			</Deal>			<Deal>				<DealTerms>					<CommercialModelType>AdvertisementSupportedModel</CommercialModelType>					<Usage>						<UseType>NonInteractiveStream</UseType>						<UseType>OnDemandStream</UseType>					</Usage>					<TerritoryCode>DE</TerritoryCode>					<ValidityPeriod>						<StartDate>2010-02-23</StartDate>					</ValidityPeriod>				</DealTerms>			</Deal>			<Deal>				<DealTerms>					<CommercialModelType>SubscriptionModel</CommercialModelType>					<Usage>						<UseType>NonInteractiveStream</UseType>						<UseType>OnDemandStream</UseType>						<UseType>ConditionalDownload</UseType>					</Usage>					<TerritoryCode>DE</TerritoryCode>					<ValidityPeriod>						<StartDate>2010-02-23</StartDate>					</ValidityPeriod>				</DealTerms>			</Deal>			<Deal>				<DealTerms>					<CommercialModelType>PayAsYouGoModel</CommercialModelType>					<Usage>						<UseType>PermanentDownload</UseType>					</Usage>					<TerritoryCode>DE</TerritoryCode>					<PriceInformation>						<PriceType Namespace="DPID:PADPIDA2007050901U">S01</PriceType>					</PriceInformation>					<ValidityPeriod>						<StartDate>2010-02-23</StartDate>					</ValidityPeriod>				</DealTerms>			</Deal>			<Deal>				<DealTerms>					<CommercialModelType>AdvertisementSupportedModel</CommercialModelType>					<Usage>						<UseType>NonInteractiveStream</UseType>						<UseType>OnDemandStream</UseType>					</Usage>					<TerritoryCode>FR</TerritoryCode>					<ValidityPeriod>						<StartDate>2010-02-23</StartDate>					</ValidityPeriod>				</DealTerms>			</Deal>			<Deal>				<DealTerms>					<CommercialModelType>SubscriptionModel</CommercialModelType>					<Usage>						<UseType>NonInteractiveStream</UseType>						<UseType>OnDemandStream</UseType>						<UseType>ConditionalDownload</UseType>					</Usage>					<TerritoryCode>FR</TerritoryCode>					<ValidityPeriod>						<StartDate>2010-02-23</StartDate>					</ValidityPeriod>				</DealTerms>			</Deal>			<Deal>				<DealTerms>					<CommercialModelType>PayAsYouGoModel</CommercialModelType>					<Usage>						<UseType>PermanentDownload</UseType>					</Usage>					<TerritoryCode>FR</TerritoryCode>					<PriceInformation>						<PriceType Namespace="DPID:PADPIDA2007050901U">S01</PriceType>					</PriceInformation>					<ValidityPeriod>						<StartDate>2010-02-23</StartDate>					</ValidityPeriod>				</DealTerms>			</Deal>			<Deal>				<DealTerms>					<CommercialModelType>AdvertisementSupportedModel</CommercialModelType>					<Usage>						<UseType>NonInteractiveStream</UseType>						<UseType>OnDemandStream</UseType>					</Usage>					<TerritoryCode>GB</TerritoryCode>					<ValidityPeriod>						<StartDate>2010-02-23</StartDate>					</ValidityPeriod>				</DealTerms>			</Deal>			<Deal>				<DealTerms>					<CommercialModelType>SubscriptionModel</CommercialModelType>					<Usage>						<UseType>NonInteractiveStream</UseType>						<UseType>OnDemandStream</UseType>						<UseType>ConditionalDownload</UseType>					</Usage>					<TerritoryCode>GB</TerritoryCode>					<ValidityPeriod>						<StartDate>2010-02-23</StartDate>					</ValidityPeriod>				</DealTerms>			</Deal>			<Deal>				<DealTerms>					<CommercialModelType>PayAsYouGoModel</CommercialModelType>					<Usage>						<UseType>PermanentDownload</UseType>					</Usage>					<TerritoryCode>GB</TerritoryCode>					<PriceInformation>						<PriceType Namespace="DPID:PADPIDA2007050901U">S01</PriceType>					</PriceInformation>					<ValidityPeriod>						<StartDate>2010-02-23</StartDate>					</ValidityPeriod>				</DealTerms>			</Deal>			<Deal>				<DealTerms>					<CommercialModelType>AdvertisementSupportedModel</CommercialModelType>					<Usage>						<UseType>NonInteractiveStream</UseType>						<UseType>OnDemandStream</UseType>					</Usage>					<TerritoryCode>US</TerritoryCode>					<ValidityPeriod>						<StartDate>2010-02-23</StartDate>					</ValidityPeriod>				</DealTerms>			</Deal>			<Deal>				<DealTerms>					<CommercialModelType>SubscriptionModel</CommercialModelType>					<Usage>						<UseType>NonInteractiveStream</UseType>						<UseType>OnDemandStream</UseType>						<UseType>ConditionalDownload</UseType>					</Usage>					<TerritoryCode>US</TerritoryCode>					<ValidityPeriod>						<StartDate>2010-02-23</StartDate>					</ValidityPeriod>				</DealTerms>			</Deal>			<Deal>				<DealTerms>					<CommercialModelType>PayAsYouGoModel</CommercialModelType>					<Usage>						<UseType>PermanentDownload</UseType>					</Usage>					<TerritoryCode>US</TerritoryCode>					<PriceInformation>						<PriceType Namespace="DPID:PADPIDA2007050901U">S1</PriceType>					</PriceInformation>					<ValidityPeriod>						<StartDate>2010-02-23</StartDate>					</ValidityPeriod>				</DealTerms>			</Deal>			<EffectiveDate>2012-05-09</EffectiveDate>		</ReleaseDeal>		<ReleaseDeal>			<DealReleaseReference>R5</DealReleaseReference>			<Deal>				<DealTerms>					<CommercialModelType>AdvertisementSupportedModel</CommercialModelType>					<Usage>						<UseType>NonInteractiveStream</UseType>						<UseType>OnDemandStream</UseType>					</Usage>					<TerritoryCode>CA</TerritoryCode>					<ValidityPeriod>						<StartDate>2010-02-23</StartDate>					</ValidityPeriod>				</DealTerms>			</Deal>			<Deal>				<DealTerms>					<CommercialModelType>SubscriptionModel</CommercialModelType>					<Usage>						<UseType>NonInteractiveStream</UseType>						<UseType>OnDemandStream</UseType>						<UseType>ConditionalDownload</UseType>					</Usage>					<TerritoryCode>CA</TerritoryCode>					<ValidityPeriod>						<StartDate>2010-02-23</StartDate>					</ValidityPeriod>				</DealTerms>			</Deal>			<Deal>				<DealTerms>					<CommercialModelType>PayAsYouGoModel</CommercialModelType>					<Usage>						<UseType>PermanentDownload</UseType>					</Usage>					<TerritoryCode>CA</TerritoryCode>					<PriceInformation>						<PriceType Namespace="DPID:PADPIDA2007050901U">S01</PriceType>					</PriceInformation>					<ValidityPeriod>						<StartDate>2010-02-23</StartDate>					</ValidityPeriod>				</DealTerms>			</Deal>			<Deal>				<DealTerms>					<CommercialModelType>AdvertisementSupportedModel</CommercialModelType>					<Usage>						<UseType>NonInteractiveStream</UseType>						<UseType>OnDemandStream</UseType>					</Usage>					<TerritoryCode>DE</TerritoryCode>					<ValidityPeriod>						<StartDate>2010-02-23</StartDate>					</ValidityPeriod>				</DealTerms>			</Deal>			<Deal>				<DealTerms>					<CommercialModelType>SubscriptionModel</CommercialModelType>					<Usage>						<UseType>NonInteractiveStream</UseType>						<UseType>OnDemandStream</UseType>						<UseType>ConditionalDownload</UseType>					</Usage>					<TerritoryCode>DE</TerritoryCode>					<ValidityPeriod>						<StartDate>2010-02-23</StartDate>					</ValidityPeriod>				</DealTerms>			</Deal>			<Deal>				<DealTerms>					<CommercialModelType>PayAsYouGoModel</CommercialModelType>					<Usage>						<UseType>PermanentDownload</UseType>					</Usage>					<TerritoryCode>DE</TerritoryCode>					<PriceInformation>						<PriceType Namespace="DPID:PADPIDA2007050901U">S01</PriceType>					</PriceInformation>					<ValidityPeriod>						<StartDate>2010-02-23</StartDate>					</ValidityPeriod>				</DealTerms>			</Deal>			<Deal>				<DealTerms>					<CommercialModelType>AdvertisementSupportedModel</CommercialModelType>					<Usage>						<UseType>NonInteractiveStream</UseType>						<UseType>OnDemandStream</UseType>					</Usage>					<TerritoryCode>FR</TerritoryCode>					<ValidityPeriod>						<StartDate>2010-02-23</StartDate>					</ValidityPeriod>				</DealTerms>			</Deal>			<Deal>				<DealTerms>					<CommercialModelType>SubscriptionModel</CommercialModelType>					<Usage>						<UseType>NonInteractiveStream</UseType>						<UseType>OnDemandStream</UseType>						<UseType>ConditionalDownload</UseType>					</Usage>					<TerritoryCode>FR</TerritoryCode>					<ValidityPeriod>						<StartDate>2010-02-23</StartDate>					</ValidityPeriod>				</DealTerms>			</Deal>			<Deal>				<DealTerms>					<CommercialModelType>PayAsYouGoModel</CommercialModelType>					<Usage>						<UseType>PermanentDownload</UseType>					</Usage>					<TerritoryCode>FR</TerritoryCode>					<PriceInformation>						<PriceType Namespace="DPID:PADPIDA2007050901U">S01</PriceType>					</PriceInformation>					<ValidityPeriod>						<StartDate>2010-02-23</StartDate>					</ValidityPeriod>				</DealTerms>			</Deal>			<Deal>				<DealTerms>					<CommercialModelType>AdvertisementSupportedModel</CommercialModelType>					<Usage>						<UseType>NonInteractiveStream</UseType>						<UseType>OnDemandStream</UseType>					</Usage>					<TerritoryCode>GB</TerritoryCode>					<ValidityPeriod>						<StartDate>2010-02-23</StartDate>					</ValidityPeriod>				</DealTerms>			</Deal>			<Deal>				<DealTerms>					<CommercialModelType>SubscriptionModel</CommercialModelType>					<Usage>						<UseType>NonInteractiveStream</UseType>						<UseType>OnDemandStream</UseType>						<UseType>ConditionalDownload</UseType>					</Usage>					<TerritoryCode>GB</TerritoryCode>					<ValidityPeriod>						<StartDate>2010-02-23</StartDate>					</ValidityPeriod>				</DealTerms>			</Deal>			<Deal>				<DealTerms>					<CommercialModelType>PayAsYouGoModel</CommercialModelType>					<Usage>						<UseType>PermanentDownload</UseType>					</Usage>					<TerritoryCode>GB</TerritoryCode>					<PriceInformation>						<PriceType Namespace="DPID:PADPIDA2007050901U">S01</PriceType>					</PriceInformation>					<ValidityPeriod>						<StartDate>2010-02-23</StartDate>					</ValidityPeriod>				</DealTerms>			</Deal>			<Deal>				<DealTerms>					<CommercialModelType>AdvertisementSupportedModel</CommercialModelType>					<Usage>						<UseType>NonInteractiveStream</UseType>						<UseType>OnDemandStream</UseType>					</Usage>					<TerritoryCode>US</TerritoryCode>					<ValidityPeriod>						<StartDate>2010-02-23</StartDate>					</ValidityPeriod>				</DealTerms>			</Deal>			<Deal>				<DealTerms>					<CommercialModelType>SubscriptionModel</CommercialModelType>					<Usage>						<UseType>NonInteractiveStream</UseType>						<UseType>OnDemandStream</UseType>						<UseType>ConditionalDownload</UseType>					</Usage>					<TerritoryCode>US</TerritoryCode>					<ValidityPeriod>						<StartDate>2010-02-23</StartDate>					</ValidityPeriod>				</DealTerms>			</Deal>			<Deal>				<DealTerms>					<CommercialModelType>PayAsYouGoModel</CommercialModelType>					<Usage>						<UseType>PermanentDownload</UseType>					</Usage>					<TerritoryCode>US</TerritoryCode>					<PriceInformation>						<PriceType Namespace="DPID:PADPIDA2007050901U">S1</PriceType>					</PriceInformation>					<ValidityPeriod>						<StartDate>2010-02-23</StartDate>					</ValidityPeriod>				</DealTerms>			</Deal>			<EffectiveDate>2012-05-09</EffectiveDate>		</ReleaseDeal>		<ReleaseDeal>			<DealReleaseReference>R6</DealReleaseReference>			<Deal>				<DealTerms>					<CommercialModelType>AdvertisementSupportedModel</CommercialModelType>					<Usage>						<UseType>NonInteractiveStream</UseType>						<UseType>OnDemandStream</UseType>					</Usage>					<TerritoryCode>CA</TerritoryCode>					<ValidityPeriod>						<StartDate>2010-02-23</StartDate>					</ValidityPeriod>				</DealTerms>			</Deal>			<Deal>				<DealTerms>					<CommercialModelType>SubscriptionModel</CommercialModelType>					<Usage>						<UseType>NonInteractiveStream</UseType>						<UseType>OnDemandStream</UseType>						<UseType>ConditionalDownload</UseType>					</Usage>					<TerritoryCode>CA</TerritoryCode>					<ValidityPeriod>						<StartDate>2010-02-23</StartDate>					</ValidityPeriod>				</DealTerms>			</Deal>			<Deal>				<DealTerms>					<CommercialModelType>PayAsYouGoModel</CommercialModelType>					<Usage>						<UseType>PermanentDownload</UseType>					</Usage>					<TerritoryCode>CA</TerritoryCode>					<PriceInformation>						<PriceType Namespace="DPID:PADPIDA2007050901U">S01</PriceType>					</PriceInformation>					<ValidityPeriod>						<StartDate>2010-02-23</StartDate>					</ValidityPeriod>				</DealTerms>			</Deal>			<Deal>				<DealTerms>					<CommercialModelType>AdvertisementSupportedModel</CommercialModelType>					<Usage>						<UseType>NonInteractiveStream</UseType>						<UseType>OnDemandStream</UseType>					</Usage>					<TerritoryCode>DE</TerritoryCode>					<ValidityPeriod>						<StartDate>2010-02-23</StartDate>					</ValidityPeriod>				</DealTerms>			</Deal>			<Deal>				<DealTerms>					<CommercialModelType>SubscriptionModel</CommercialModelType>					<Usage>						<UseType>NonInteractiveStream</UseType>						<UseType>OnDemandStream</UseType>						<UseType>ConditionalDownload</UseType>					</Usage>					<TerritoryCode>DE</TerritoryCode>					<ValidityPeriod>						<StartDate>2010-02-23</StartDate>					</ValidityPeriod>				</DealTerms>			</Deal>			<Deal>				<DealTerms>					<CommercialModelType>PayAsYouGoModel</CommercialModelType>					<Usage>						<UseType>PermanentDownload</UseType>					</Usage>					<TerritoryCode>DE</TerritoryCode>					<PriceInformation>						<PriceType Namespace="DPID:PADPIDA2007050901U">S01</PriceType>					</PriceInformation>					<ValidityPeriod>						<StartDate>2010-02-23</StartDate>					</ValidityPeriod>				</DealTerms>			</Deal>			<Deal>				<DealTerms>					<CommercialModelType>AdvertisementSupportedModel</CommercialModelType>					<Usage>						<UseType>NonInteractiveStream</UseType>						<UseType>OnDemandStream</UseType>					</Usage>					<TerritoryCode>FR</TerritoryCode>					<ValidityPeriod>						<StartDate>2010-02-23</StartDate>					</ValidityPeriod>				</DealTerms>			</Deal>			<Deal>				<DealTerms>					<CommercialModelType>SubscriptionModel</CommercialModelType>					<Usage>						<UseType>NonInteractiveStream</UseType>						<UseType>OnDemandStream</UseType>						<UseType>ConditionalDownload</UseType>					</Usage>					<TerritoryCode>FR</TerritoryCode>					<ValidityPeriod>						<StartDate>2010-02-23</StartDate>					</ValidityPeriod>				</DealTerms>			</Deal>			<Deal>				<DealTerms>					<CommercialModelType>PayAsYouGoModel</CommercialModelType>					<Usage>						<UseType>PermanentDownload</UseType>					</Usage>					<TerritoryCode>FR</TerritoryCode>					<PriceInformation>						<PriceType Namespace="DPID:PADPIDA2007050901U">S01</PriceType>					</PriceInformation>					<ValidityPeriod>						<StartDate>2010-02-23</StartDate>					</ValidityPeriod>				</DealTerms>			</Deal>			<Deal>				<DealTerms>					<CommercialModelType>AdvertisementSupportedModel</CommercialModelType>					<Usage>						<UseType>NonInteractiveStream</UseType>						<UseType>OnDemandStream</UseType>					</Usage>					<TerritoryCode>GB</TerritoryCode>					<ValidityPeriod>						<StartDate>2010-02-23</StartDate>					</ValidityPeriod>				</DealTerms>			</Deal>			<Deal>				<DealTerms>					<CommercialModelType>SubscriptionModel</CommercialModelType>					<Usage>						<UseType>NonInteractiveStream</UseType>						<UseType>OnDemandStream</UseType>						<UseType>ConditionalDownload</UseType>					</Usage>					<TerritoryCode>GB</TerritoryCode>					<ValidityPeriod>						<StartDate>2010-02-23</StartDate>					</ValidityPeriod>				</DealTerms>			</Deal>			<Deal>				<DealTerms>					<CommercialModelType>PayAsYouGoModel</CommercialModelType>					<Usage>						<UseType>PermanentDownload</UseType>					</Usage>					<TerritoryCode>GB</TerritoryCode>					<PriceInformation>						<PriceType Namespace="DPID:PADPIDA2007050901U">S01</PriceType>					</PriceInformation>					<ValidityPeriod>						<StartDate>2010-02-23</StartDate>					</ValidityPeriod>				</DealTerms>			</Deal>			<Deal>				<DealTerms>					<CommercialModelType>AdvertisementSupportedModel</CommercialModelType>					<Usage>						<UseType>NonInteractiveStream</UseType>						<UseType>OnDemandStream</UseType>					</Usage>					<TerritoryCode>US</TerritoryCode>					<ValidityPeriod>						<StartDate>2010-02-23</StartDate>					</ValidityPeriod>				</DealTerms>			</Deal>			<Deal>				<DealTerms>					<CommercialModelType>SubscriptionModel</CommercialModelType>					<Usage>						<UseType>NonInteractiveStream</UseType>						<UseType>OnDemandStream</UseType>						<UseType>ConditionalDownload</UseType>					</Usage>					<TerritoryCode>US</TerritoryCode>					<ValidityPeriod>						<StartDate>2010-02-23</StartDate>					</ValidityPeriod>				</DealTerms>			</Deal>			<Deal>				<DealTerms>					<CommercialModelType>PayAsYouGoModel</CommercialModelType>					<Usage>						<UseType>PermanentDownload</UseType>					</Usage>					<TerritoryCode>US</TerritoryCode>					<PriceInformation>						<PriceType Namespace="DPID:PADPIDA2007050901U">S1</PriceType>					</PriceInformation>					<ValidityPeriod>						<StartDate>2010-02-23</StartDate>					</ValidityPeriod>				</DealTerms>			</Deal>			<EffectiveDate>2012-05-09</EffectiveDate>		</ReleaseDeal>		<ReleaseDeal>			<DealReleaseReference>R7</DealReleaseReference>			<Deal>				<DealTerms>					<CommercialModelType>AdvertisementSupportedModel</CommercialModelType>					<Usage>						<UseType>NonInteractiveStream</UseType>						<UseType>OnDemandStream</UseType>					</Usage>					<TerritoryCode>CA</TerritoryCode>					<ValidityPeriod>						<StartDate>2010-02-23</StartDate>					</ValidityPeriod>				</DealTerms>			</Deal>			<Deal>				<DealTerms>					<CommercialModelType>SubscriptionModel</CommercialModelType>					<Usage>						<UseType>NonInteractiveStream</UseType>						<UseType>OnDemandStream</UseType>						<UseType>ConditionalDownload</UseType>					</Usage>					<TerritoryCode>CA</TerritoryCode>					<ValidityPeriod>						<StartDate>2010-02-23</StartDate>					</ValidityPeriod>				</DealTerms>			</Deal>			<Deal>				<DealTerms>					<CommercialModelType>PayAsYouGoModel</CommercialModelType>					<Usage>						<UseType>PermanentDownload</UseType>					</Usage>					<TerritoryCode>CA</TerritoryCode>					<PriceInformation>						<PriceType Namespace="DPID:PADPIDA2007050901U">S01</PriceType>					</PriceInformation>					<ValidityPeriod>						<StartDate>2010-02-23</StartDate>					</ValidityPeriod>				</DealTerms>			</Deal>			<Deal>				<DealTerms>					<CommercialModelType>AdvertisementSupportedModel</CommercialModelType>					<Usage>						<UseType>NonInteractiveStream</UseType>						<UseType>OnDemandStream</UseType>					</Usage>					<TerritoryCode>DE</TerritoryCode>					<ValidityPeriod>						<StartDate>2010-02-23</StartDate>					</ValidityPeriod>				</DealTerms>			</Deal>			<Deal>				<DealTerms>					<CommercialModelType>SubscriptionModel</CommercialModelType>					<Usage>						<UseType>NonInteractiveStream</UseType>						<UseType>OnDemandStream</UseType>						<UseType>ConditionalDownload</UseType>					</Usage>					<TerritoryCode>DE</TerritoryCode>					<ValidityPeriod>						<StartDate>2010-02-23</StartDate>					</ValidityPeriod>				</DealTerms>			</Deal>			<Deal>				<DealTerms>					<CommercialModelType>PayAsYouGoModel</CommercialModelType>					<Usage>						<UseType>PermanentDownload</UseType>					</Usage>					<TerritoryCode>DE</TerritoryCode>					<PriceInformation>						<PriceType Namespace="DPID:PADPIDA2007050901U">S01</PriceType>					</PriceInformation>					<ValidityPeriod>						<StartDate>2010-02-23</StartDate>					</ValidityPeriod>				</DealTerms>			</Deal>			<Deal>				<DealTerms>					<CommercialModelType>AdvertisementSupportedModel</CommercialModelType>					<Usage>						<UseType>NonInteractiveStream</UseType>						<UseType>OnDemandStream</UseType>					</Usage>					<TerritoryCode>FR</TerritoryCode>					<ValidityPeriod>						<StartDate>2010-02-23</StartDate>					</ValidityPeriod>				</DealTerms>			</Deal>			<Deal>				<DealTerms>					<CommercialModelType>SubscriptionModel</CommercialModelType>					<Usage>						<UseType>NonInteractiveStream</UseType>						<UseType>OnDemandStream</UseType>						<UseType>ConditionalDownload</UseType>					</Usage>					<TerritoryCode>FR</TerritoryCode>					<ValidityPeriod>						<StartDate>2010-02-23</StartDate>					</ValidityPeriod>				</DealTerms>			</Deal>			<Deal>				<DealTerms>					<CommercialModelType>PayAsYouGoModel</CommercialModelType>					<Usage>						<UseType>PermanentDownload</UseType>					</Usage>					<TerritoryCode>FR</TerritoryCode>					<PriceInformation>						<PriceType Namespace="DPID:PADPIDA2007050901U">S01</PriceType>					</PriceInformation>					<ValidityPeriod>						<StartDate>2010-02-23</StartDate>					</ValidityPeriod>				</DealTerms>			</Deal>			<Deal>				<DealTerms>					<CommercialModelType>AdvertisementSupportedModel</CommercialModelType>					<Usage>						<UseType>NonInteractiveStream</UseType>						<UseType>OnDemandStream</UseType>					</Usage>					<TerritoryCode>GB</TerritoryCode>					<ValidityPeriod>						<StartDate>2010-02-23</StartDate>					</ValidityPeriod>				</DealTerms>			</Deal>			<Deal>				<DealTerms>					<CommercialModelType>SubscriptionModel</CommercialModelType>					<Usage>						<UseType>NonInteractiveStream</UseType>						<UseType>OnDemandStream</UseType>						<UseType>ConditionalDownload</UseType>					</Usage>					<TerritoryCode>GB</TerritoryCode>					<ValidityPeriod>						<StartDate>2010-02-23</StartDate>					</ValidityPeriod>				</DealTerms>			</Deal>			<Deal>				<DealTerms>					<CommercialModelType>PayAsYouGoModel</CommercialModelType>					<Usage>						<UseType>PermanentDownload</UseType>					</Usage>					<TerritoryCode>GB</TerritoryCode>					<PriceInformation>						<PriceType Namespace="DPID:PADPIDA2007050901U">S01</PriceType>					</PriceInformation>					<ValidityPeriod>						<StartDate>2010-02-23</StartDate>					</ValidityPeriod>				</DealTerms>			</Deal>			<Deal>				<DealTerms>					<CommercialModelType>AdvertisementSupportedModel</CommercialModelType>					<Usage>						<UseType>NonInteractiveStream</UseType>						<UseType>OnDemandStream</UseType>					</Usage>					<TerritoryCode>US</TerritoryCode>					<ValidityPeriod>						<StartDate>2010-02-23</StartDate>					</ValidityPeriod>				</DealTerms>			</Deal>			<Deal>				<DealTerms>					<CommercialModelType>SubscriptionModel</CommercialModelType>					<Usage>						<UseType>NonInteractiveStream</UseType>						<UseType>OnDemandStream</UseType>						<UseType>ConditionalDownload</UseType>					</Usage>					<TerritoryCode>US</TerritoryCode>					<ValidityPeriod>						<StartDate>2010-02-23</StartDate>					</ValidityPeriod>				</DealTerms>			</Deal>			<Deal>				<DealTerms>					<CommercialModelType>PayAsYouGoModel</CommercialModelType>					<Usage>						<UseType>PermanentDownload</UseType>					</Usage>					<TerritoryCode>US</TerritoryCode>					<PriceInformation>						<PriceType Namespace="DPID:PADPIDA2007050901U">S1</PriceType>					</PriceInformation>					<ValidityPeriod>						<StartDate>2010-02-23</StartDate>					</ValidityPeriod>				</DealTerms>			</Deal>			<EffectiveDate>2012-05-09</EffectiveDate>		</ReleaseDeal>	</DealList></ernm:NewReleaseMessage>